csb43/.gitignore
csb43/__init__.py
csb43/_version.py
csb43/formats.py
csb43/py.typed
csb43/aeb43/__init__.py
csb43/aeb43/account.py
csb43/aeb43/batch.py
csb43/aeb43/closing.py
csb43/aeb43/closing_account.py
csb43/aeb43/exchange.py
csb43/aeb43/item.py
csb43/aeb43/sepa_debit.py
csb43/aeb43/sepa_transfer.py
csb43/aeb43/transaction.py
csb43/aeb43/fields/__init__.py
csb43/aeb43/fields/currency.py
csb43/aeb43/fields/date.py
csb43/aeb43/fields/information_mode.py
csb43/aeb43/fields/integer.py
csb43/aeb43/fields/money.py
csb43/aeb43/fields/nested.py
csb43/aeb43/fields/string.py
csb43/aeb43/record/__init__.py
csb43/aeb43/record/context.py
csb43/aeb43/record/errors.py
csb43/csb43/__init__.py
csb43/csb43/account.py
csb43/csb43/csb_file.py
csb43/csb43/exchange.py
csb43/csb43/item.py
csb43/csb43/record.py
csb43/csb43/transaction.py
csb43/homebank/__init__.py
csb43/homebank/converter.py
csb43/i18n/__init__.py
csb43/i18n/messages.pot
csb43/i18n/es/__init__.py
csb43/i18n/es/LC_MESSAGES/__init__.py
csb43/i18n/es/LC_MESSAGES/messages.mo
csb43/i18n/es/LC_MESSAGES/messages.mo.license
csb43/i18n/es/LC_MESSAGES/messages.po
csb43/ofx/__init__.py
csb43/ofx/balance.py
csb43/ofx/bank_account.py
csb43/ofx/base.py
csb43/ofx/converter.py
csb43/ofx/file.py
csb43/ofx/payee.py
csb43/ofx/transaction.py
csb43/tests/__init__.py
csb43/tests/conftest.py
csb43/tests/sample_sepa.csb
csb43/tests/sample_sepa.csb.license
csb43/tests/samples.py
csb43/tests/test_aeb43_account.py
csb43/tests/test_aeb43_batch.py
csb43/tests/test_aeb43_closing_account.py
csb43/tests/test_aeb43_context.py
csb43/tests/test_aeb43_exchange.py
csb43/tests/test_aeb43_item.py
csb43/tests/test_aeb43_sepa_debit.py
csb43/tests/test_aeb43_sepa_transfer.py
csb43/tests/test_aeb43_transaction.py
csb43/tests/test_aeb43ofx.py
csb43/tests/test_cmd.py
csb43/tests/test_csb2ofx.py
csb43/tests/test_csb_account.py
csb43/tests/test_csb_exchange.py
csb43/tests/test_csb_file.py
csb43/tests/test_csb_item.py
csb43/tests/test_csb_transaction.py
csb43-0.10.1.dist-info/LICENSE
csb43-0.10.1.dist-info/METADATA
csb43-0.10.1.dist-info/WHEEL
csb43-0.10.1.dist-info/entry_points.txt
csb43-0.10.1.dist-info/top_level.txt
csb43-0.10.1.dist-info/RECORD
