Metadata-Version: 2.1
Name: csb43
Version: 0.10.1
Summary: Parsing and validation utilites for the Spanish standard norm 43 by the 'Consejo Superior Bancario' (CSB) / 'Asociación Española de Banca' (AEB) for storing bank account transactions | [es] Herramientas para leer y validar datos almacenados siguiendo la norma 43 del Consejo Superior Bancario (CSB) / Asociación Española de Banca (CSB).
Author-email: wmj <wmj.py@gmx.com>
License: LGPL-3.0-or-later
Project-URL: BugReports, https://bitbucket.org/wmj/csb43/issues
Project-URL: Source, https://bitbucket.org/wmj/csb43
Project-URL: Documentation, https://csb43.readthedocs.io
Keywords: csb,csb43,aeb,aeb43,homebank,ofx,Spanish bank,ods,tsv,xls,xlsx,excel,yaml,json,html
Classifier: Programming Language :: Python
Classifier: Programming Language :: Python :: 3.8
Classifier: Programming Language :: Python :: 3.9
Classifier: Programming Language :: Python :: 3.10
Classifier: Programming Language :: Python :: 3.11
Classifier: Programming Language :: Python :: 3.12
Classifier: Development Status :: 4 - Beta
Classifier: Environment :: Console
Classifier: Topic :: Utilities
Classifier: Topic :: Office/Business :: Financial
Classifier: License :: OSI Approved :: GNU Lesser General Public License v3 or later (LGPLv3+)
Requires-Python: >=3.8
License-File: LICENSE
Requires-Dist: pycountry ~=24.6.1
Requires-Dist: deprecated ~=1.2.14
Requires-Dist: importlib-resources ; python_version < "3.9"
Provides-Extra: all
Requires-Dist: csb43[formats,yaml] ; extra == 'all'
Provides-Extra: basic_formats
Requires-Dist: tablib ~=3.6.1 ; extra == 'basic_formats'
Provides-Extra: dev
Requires-Dist: build ; extra == 'dev'
Requires-Dist: sphinx ; extra == 'dev'
Requires-Dist: reuse ; extra == 'dev'
Requires-Dist: csb43[docs,test] ; extra == 'dev'
Provides-Extra: docs
Requires-Dist: sphinx ; extra == 'docs'
Provides-Extra: formats
Requires-Dist: tablib[all] ; extra == 'formats'
Requires-Dist: csb43[basic_formats] ; extra == 'formats'
Provides-Extra: test
Requires-Dist: lxml ; extra == 'test'
Requires-Dist: pytest ; extra == 'test'
Requires-Dist: tablib[ods,xls,xlsx] ; extra == 'test'
Requires-Dist: csb43[basic_formats,yaml] ; extra == 'test'
Provides-Extra: yaml
Requires-Dist: PyYAML ; extra == 'yaml'
